klove/__about__.py
klove/__init__.py
klove/bztools.py
klove/core.py
klove/eig.py
klove/special.py
klove/viz.py
klove-0.1.0.dist-info/LICENSE.txt
klove-0.1.0.dist-info/METADATA
klove-0.1.0.dist-info/WHEEL
klove-0.1.0.dist-info/top_level.txt
klove-0.1.0.dist-info/RECORD
