Metadata-Version: 2.1
Name: klove
Version: 0.1.0
Summary: Waves on elastic plates
Home-page: https://gitlab.com/benvial/klove
Author: Benjamin Vial
License: GPL-3.0-or-later
Project-URL: Code, https://gitlab.com/benvial/klove
Project-URL: Documentation, https://benvial.gitlab.io/klove
Project-URL: Issues, https://gitlab.com/benvial/klove/issues
Keywords: elastic plates,auto-differentiation,linear algebra
Classifier: Development Status :: 4 - Beta
Classifier: Intended Audience :: Science/Research
Classifier: License :: OSI Approved :: GNU General Public License v3 or later (GPLv3+)
Classifier: Operating System :: OS Independent
Classifier: Programming Language :: Python
Classifier: Programming Language :: Python :: 3
Classifier: Programming Language :: Python :: 3.8
Classifier: Programming Language :: Python :: 3.9
Classifier: Programming Language :: Python :: 3.10
Classifier: Programming Language :: Python :: 3.11
Classifier: Topic :: Scientific/Engineering
Classifier: Topic :: Scientific/Engineering :: Mathematics
Classifier: Topic :: Utilities
Requires-Python: >=3.8
License-File: LICENSE.txt
Requires-Dist: matplotlib
Requires-Dist: numpy
Requires-Dist: scipy
Requires-Dist: scikit-image
Provides-Extra: diff
Requires-Dist: numdiff >=0.0.1 ; extra == 'diff'
Provides-Extra: full
Requires-Dist: klove[diff] ; extra == 'full'
